odoo/addons/l10n_es_aeat_mod390_vat_prorate/README.rst
odoo/addons/l10n_es_aeat_mod390_vat_prorate/__init__.py
odoo/addons/l10n_es_aeat_mod390_vat_prorate/__manifest__.py
odoo/addons/l10n_es_aeat_mod390_vat_prorate/data/aeat_export_mod390_prorate_data.xml
odoo/addons/l10n_es_aeat_mod390_vat_prorate/i18n/l10n_es_aeat_mod390_vat_prorate.pot
odoo/addons/l10n_es_aeat_mod390_vat_prorate/models/__init__.py
odoo/addons/l10n_es_aeat_mod390_vat_prorate/models/mod390.py
odoo/addons/l10n_es_aeat_mod390_vat_prorate/models/mod390_line_prorate.py
odoo/addons/l10n_es_aeat_mod390_vat_prorate/readme/CONTRIBUTORS.rst
odoo/addons/l10n_es_aeat_mod390_vat_prorate/readme/DESCRIPTION.rst
odoo/addons/l10n_es_aeat_mod390_vat_prorate/readme/ROADMAP.rst
odoo/addons/l10n_es_aeat_mod390_vat_prorate/readme/USAGE.rst
odoo/addons/l10n_es_aeat_mod390_vat_prorate/security/ir.model.access.csv
odoo/addons/l10n_es_aeat_mod390_vat_prorate/static/description/icon.png
odoo/addons/l10n_es_aeat_mod390_vat_prorate/static/description/icon.svg
odoo/addons/l10n_es_aeat_mod390_vat_prorate/static/description/index.html
odoo/addons/l10n_es_aeat_mod390_vat_prorate/tests/__init__.py
odoo/addons/l10n_es_aeat_mod390_vat_prorate/tests/test_l10n_es_aeat_mod390_vat_prorate.py
odoo/addons/l10n_es_aeat_mod390_vat_prorate/views/mod390_view.xml
odoo12_addon_l10n_es_aeat_mod390_vat_prorate-12.0.1.0.0.99.dev2.dist-info/METADATA
odoo12_addon_l10n_es_aeat_mod390_vat_prorate-12.0.1.0.0.99.dev2.dist-info/WHEEL
odoo12_addon_l10n_es_aeat_mod390_vat_prorate-12.0.1.0.0.99.dev2.dist-info/top_level.txt
odoo12_addon_l10n_es_aeat_mod390_vat_prorate-12.0.1.0.0.99.dev2.dist-info/RECORD
